updt/__init__.py
updt/__main__.py
updt-0.0.0.dist-info/METADATA
updt-0.0.0.dist-info/WHEEL
updt-0.0.0.dist-info/entry_points.txt
updt-0.0.0.dist-info/top_level.txt
updt-0.0.0.dist-info/RECORD
